{"id":"idU6lzwMYA","name":"ClickUp","domain":"clickup.com","claimed":false,"description":"ClickUp is an app that brings tasks, docs, spreadsheets, goal tracking, resources, and an inbox, together in one place.","links":[{"name":"youtube","url":"https://youtube.com/channel/UCJC7egHqghye211WgTuXMAw"},{"name":"twitter","url":"https://twitter.com/clickup_app"},{"name":"instagram","url":"https://instagram.com/clickup_app"},{"name":"linkedin","url":"https://linkedin.com/company/clickup.co"},{"name":"facebook","url":"https://facebook.com/clickupprojectmanagement"}],"logos":[{"type":"logo","theme":null,"formats":[{"src":"https://asset.brandfetch.io/idU6lzwMYA/id1D_zzjrg.svg","background":"transparent","format":"svg","size":2591},{"src":"https://asset.brandfetch.io/idU6lzwMYA/id5juIsr7U.png","background":"transparent","format":"png","height":195,"width":800,"size":17532}]},{"type":"symbol","theme":null,"formats":[{"src":"https://asset.brandfetch.io/idU6lzwMYA/idMaCKxlWy.svg","background":"transparent","format":"svg","size":853},{"src":"https://asset.brandfetch.io/idU6lzwMYA/id8HYxuh60.png","background":"transparent","format":"png","height":954,"width":800,"size":53310}]},{"type":"icon","theme":null,"formats":[{"src":"https://asset.brandfetch.io/idU6lzwMYA/id20nW6OHw.jpeg","background":null,"format":"jpeg","height":400,"width":400,"size":8037}]}],"colors":[{"hex":"#292d34","type":"dark","brightness":45},{"hex":"#fafbfc","type":"light","brightness":251},{"hex":"#5b5b5b","type":"accent","brightness":91}],"fonts":[{"name":"Gotham Pro","type":"title","origin":"custom","originId":null,"weights":[]},{"name":"Gotham Pro","type":"body","origin":"custom","originId":null,"weights":[]}],"images":[{"type":"banner","formats":[{"src":"https://asset.brandfetch.io/idU6lzwMYA/id43VhMp8S.jpeg","background":null,"format":"jpeg","height":500,"width":1500,"size":33110}]}]}